influxobject/__init__.py
influxobject/influxobject_tools.py
influxobject/influxpoint.py
influxobject/module1.py
influxobject-0.0.9.dist-info/METADATA
influxobject-0.0.9.dist-info/WHEEL
influxobject-0.0.9.dist-info/licenses/LICENSE
influxobject-0.0.9.dist-info/RECORD
