Metadata-Version: 2.4
Name: influxobject
Version: 0.0.9
Summary: Influx Object Package
License: MIT
License-File: LICENSE
Keywords: influx,json,package
Author: Jasper Koehorst
Author-email: jasper.koehorst@wur.nl
Requires-Python: >=3.9,<4.0
Classifier: Development Status :: 4 - Beta
Classifier: Intended Audience :: Developers
Classifier: License :: OSI Approved :: MIT License
Classifier: Operating System :: OS Independent
Classifier: Programming Language :: Python :: 3
Classifier: Programming Language :: Python :: 3.9
Classifier: Programming Language :: Python :: 3.10
Classifier: Programming Language :: Python :: 3.11
Classifier: Programming Language :: Python :: 3.12
Classifier: Programming Language :: Python :: 3.13
Classifier: Programming Language :: Python :: 3.14
Classifier: Programming Language :: Python :: 3 :: Only
Classifier: Topic :: Software Development :: Build Tools
Provides-Extra: dev
Project-URL: Documentation, https://gitlab.com/m-unlock/influx-object
Project-URL: Homepage, https://gitlab.com/m-unlock/influx-object
Project-URL: Repository, https://gitlab.com/m-unlock/influx-object
